{
  "updatedAt": "2026-04-24T14:16:44.835Z",
  "updatedAtJST": "2026-04-24 23:16 JST",
  "stocks": [
    {
      "ticker": "7203",
      "price": 3067,
      "change": -1.79,
      "ma5": 3210,
      "ma25": 3289,
      "ma75": 3468,
      "trend": "下降",
      "rsi": 37,
      "macd": -59.8,
      "macdSignal": -43,
      "macdHist": -16.9,
      "volume": 22659400,
      "volAvg": 19838070,
      "volRatio": 1.14,
      "signal": "強い売り",
      "strength": 20,
      "sparkline": [
        3390,
        3280,
        3191,
        3123,
        3067
      ]
    },
    {
      "ticker": "6758",
      "price": 3208,
      "change": -1.69,
      "ma5": 3309,
      "ma25": 3298,
      "ma75": 3381,
      "trend": "横ばい",
      "rsi": 43,
      "macd": -13.5,
      "macdSignal": -8.1,
      "macdHist": -5.4,
      "volume": 14835500,
      "volAvg": 15274380,
      "volRatio": 0.97,
      "signal": "売り",
      "strength": 35,
      "sparkline": [
        3384,
        3346,
        3343,
        3263,
        3208
      ]
    },
    {
      "ticker": "9984",
      "price": 5963,
      "change": 2.16,
      "ma5": 5475,
      "ma25": 4178,
      "ma75": 4113,
      "trend": "上昇",
      "rsi": 90,
      "macd": 479.5,
      "macdSignal": 254.4,
      "macdHist": 225.1,
      "volume": 87686800,
      "volAvg": 67059490,
      "volRatio": 1.31,
      "signal": "買い",
      "strength": 68,
      "sparkline": [
        4774,
        5181,
        5620,
        5837,
        5963
      ]
    },
    {
      "ticker": "8306",
      "price": 2756,
      "change": 0.13,
      "ma5": 2801,
      "ma25": 2780,
      "ma75": 2806,
      "trend": "横ばい",
      "rsi": 46,
      "macd": 13.3,
      "macdSignal": 24.3,
      "macdHist": -11,
      "volume": 22067000,
      "volAvg": 38363175,
      "volRatio": 0.58,
      "signal": "売り",
      "strength": 35,
      "sparkline": [
        2871,
        2831,
        2794,
        2752,
        2756
      ]
    },
    {
      "ticker": "6861",
      "price": 63180,
      "change": -0.46,
      "ma5": 63530,
      "ma25": 60100,
      "ma75": 59729,
      "trend": "横ばい",
      "rsi": 75,
      "macd": 1215.8,
      "macdSignal": 970.2,
      "macdHist": 245.6,
      "volume": 735200,
      "volAvg": 679930,
      "volRatio": 1.08,
      "signal": "中立",
      "strength": 53,
      "sparkline": [
        64030,
        63170,
        63800,
        63470,
        63180
      ]
    },
    {
      "ticker": "4063",
      "price": 6768,
      "change": 1.56,
      "ma5": 6716,
      "ma25": 6516,
      "ma75": 6074,
      "trend": "上昇",
      "rsi": 62,
      "macd": 145,
      "macdSignal": 160,
      "macdHist": -15,
      "volume": 5016200,
      "volAvg": 8577740,
      "volRatio": 0.58,
      "signal": "買い",
      "strength": 60,
      "sparkline": [
        6773,
        6733,
        6642,
        6664,
        6768
      ]
    },
    {
      "ticker": "9432",
      "price": 152,
      "change": 0.07,
      "ma5": 152,
      "ma25": 155,
      "ma75": 154,
      "trend": "下降",
      "rsi": 26,
      "macd": -1,
      "macdSignal": -0.6,
      "macdHist": -0.4,
      "volume": 176730900,
      "volAvg": 180584530,
      "volRatio": 0.98,
      "signal": "売り",
      "strength": 32,
      "sparkline": [
        154,
        152,
        152,
        151,
        152
      ]
    },
    {
      "ticker": "7974",
      "price": 7953,
      "change": -3.25,
      "ma5": 8304,
      "ma25": 8646,
      "ma75": 8970,
      "trend": "下降",
      "rsi": 24,
      "macd": -235.4,
      "macdSignal": -211.2,
      "macdHist": -24.2,
      "volume": 14057800,
      "volAvg": 8221965,
      "volRatio": 1.71,
      "signal": "売り",
      "strength": 40,
      "sparkline": [
        8507,
        8429,
        8413,
        8220,
        7953
      ]
    },
    {
      "ticker": "6367",
      "price": 21565,
      "change": 2.25,
      "ma5": 21552,
      "ma25": 20279,
      "ma75": 19713,
      "trend": "上昇",
      "rsi": 64,
      "macd": 536.2,
      "macdSignal": 451.6,
      "macdHist": 84.6,
      "volume": 825400,
      "volAvg": 1252735,
      "volRatio": 0.66,
      "signal": "強い買い",
      "strength": 80,
      "sparkline": [
        22240,
        21630,
        21235,
        21090,
        21565
      ]
    },
    {
      "ticker": "8035",
      "price": 45850,
      "change": 0.81,
      "ma5": 45372,
      "ma25": 41648,
      "ma75": 41614,
      "trend": "上昇",
      "rsi": 74,
      "macd": 1444.7,
      "macdSignal": 1022.2,
      "macdHist": 422.5,
      "volume": 2312400,
      "volAvg": 3073900,
      "volRatio": 0.75,
      "signal": "買い",
      "strength": 68,
      "sparkline": [
        44250,
        45780,
        45500,
        45480,
        45850
      ]
    },
    {
      "ticker": "4661",
      "price": 2400,
      "change": -3.3,
      "ma5": 2545,
      "ma25": 2640,
      "ma75": 2716,
      "trend": "下降",
      "rsi": 24,
      "macd": -57.3,
      "macdSignal": -40.3,
      "macdHist": -17,
      "volume": 8297100,
      "volAvg": 4257950,
      "volRatio": 1.95,
      "signal": "売り",
      "strength": 40,
      "sparkline": [
        2644,
        2613,
        2588,
        2482,
        2400
      ]
    },
    {
      "ticker": "9983",
      "price": 70090,
      "change": 1.15,
      "ma5": 71898,
      "ma25": 67891,
      "ma75": 65978,
      "trend": "横ばい",
      "rsi": 62,
      "macd": 1971,
      "macdSignal": 2207.7,
      "macdHist": -236.7,
      "volume": 1286200,
      "volAvg": 1247870,
      "volRatio": 1.03,
      "signal": "中立",
      "strength": 45,
      "sparkline": [
        74650,
        73750,
        71710,
        69290,
        70090
      ]
    },
    {
      "ticker": "6954",
      "price": 6256,
      "change": -1.32,
      "ma5": 6418,
      "ma25": 5948,
      "ma75": 6223,
      "trend": "横ばい",
      "rsi": 71,
      "macd": 107.6,
      "macdSignal": 50.6,
      "macdHist": 57,
      "volume": 6099800,
      "volAvg": 5154145,
      "volRatio": 1.18,
      "signal": "中立",
      "strength": 53,
      "sparkline": [
        6503,
        6478,
        6511,
        6340,
        6256
      ]
    },
    {
      "ticker": "7267",
      "price": 1297,
      "change": -1.18,
      "ma5": 1323,
      "ma25": 1291,
      "ma75": 1428,
      "trend": "横ばい",
      "rsi": 58,
      "macd": -15.7,
      "macdSignal": -27.6,
      "macdHist": 11.9,
      "volume": 14795400,
      "volAvg": 21153495,
      "volRatio": 0.7,
      "signal": "買い",
      "strength": 65,
      "sparkline": [
        1341,
        1342,
        1323,
        1312,
        1297
      ]
    },
    {
      "ticker": "2802",
      "price": 4758,
      "change": 3.66,
      "ma5": 4667,
      "ma25": 4585,
      "ma75": 4410,
      "trend": "上昇",
      "rsi": 55,
      "macd": 54.7,
      "macdSignal": 58.6,
      "macdHist": -3.9,
      "volume": 4191800,
      "volAvg": 3069455,
      "volRatio": 1.37,
      "signal": "買い",
      "strength": 60,
      "sparkline": [
        4607,
        4721,
        4658,
        4590,
        4758
      ]
    },
    {
      "ticker": "4519",
      "price": 8845,
      "change": -0.91,
      "ma5": 8814,
      "ma25": 8663,
      "ma75": 9051,
      "trend": "横ばい",
      "rsi": 50,
      "macd": -57.3,
      "macdSignal": -103.4,
      "macdHist": 46,
      "volume": 4079800,
      "volAvg": 2469290,
      "volRatio": 1.65,
      "signal": "買い",
      "strength": 73,
      "sparkline": [
        8844,
        8694,
        8760,
        8926,
        8845
      ]
    },
    {
      "ticker": "6098",
      "price": 7308,
      "change": -3.35,
      "ma5": 7660,
      "ma25": 7035,
      "ma75": 6994,
      "trend": "横ばい",
      "rsi": 58,
      "macd": 223.3,
      "macdSignal": 181.3,
      "macdHist": 42.1,
      "volume": 5591600,
      "volAvg": 5584825,
      "volRatio": 1,
      "signal": "買い",
      "strength": 65,
      "sparkline": [
        7625,
        7853,
        7953,
        7561,
        7308
      ]
    },
    {
      "ticker": "7751",
      "price": 4024,
      "change": -7.9,
      "ma5": 4364,
      "ma25": 4409,
      "ma75": 4547,
      "trend": "下降",
      "rsi": 22,
      "macd": -43.6,
      "macdSignal": -21.6,
      "macdHist": -22,
      "volume": 14149200,
      "volAvg": 3603725,
      "volRatio": 3.93,
      "signal": "売り",
      "strength": 40,
      "sparkline": [
        4490,
        4484,
        4451,
        4369,
        4024
      ]
    },
    {
      "ticker": "8316",
      "price": 5347,
      "change": -0.06,
      "ma5": 5437,
      "ma25": 5399,
      "ma75": 5507,
      "trend": "横ばい",
      "rsi": 48,
      "macd": 16.8,
      "macdSignal": 34.2,
      "macdHist": -17.4,
      "volume": 7882600,
      "volAvg": 12078420,
      "volRatio": 0.65,
      "signal": "売り",
      "strength": 35,
      "sparkline": [
        5575,
        5471,
        5442,
        5350,
        5347
      ]
    },
    {
      "ticker": "8058",
      "price": 4950,
      "change": 3.3,
      "ma5": 4848,
      "ma25": 5270,
      "ma75": 5042,
      "trend": "横ばい",
      "rsi": 30,
      "macd": -111.2,
      "macdSignal": -48.9,
      "macdHist": -62.3,
      "volume": 10913900,
      "volAvg": 10607020,
      "volRatio": 1.03,
      "signal": "中立",
      "strength": 47,
      "sparkline": [
        4910,
        4844,
        4746,
        4792,
        4950
      ]
    },
    {
      "ticker": "5016",
      "price": 4625,
      "change": -0.6,
      "ma5": 4754,
      "ma25": 4195,
      "ma75": 3730,
      "trend": "横ばい",
      "rsi": 71,
      "macd": 284.9,
      "macdSignal": 285.7,
      "macdHist": -0.8,
      "volume": 19917400,
      "volAvg": 36049720,
      "volRatio": 0.55,
      "signal": "売り",
      "strength": 33,
      "sparkline": [
        4817,
        4820,
        4855,
        4653,
        4625
      ]
    },
    {
      "ticker": "2914",
      "price": 5829,
      "change": -0.63,
      "ma5": 5783,
      "ma25": 5931,
      "ma75": 5879,
      "trend": "横ばい",
      "rsi": 30,
      "macd": -32.7,
      "macdSignal": -8.9,
      "macdHist": -23.8,
      "volume": 3201700,
      "volAvg": 3920760,
      "volRatio": 0.82,
      "signal": "中立",
      "strength": 47,
      "sparkline": [
        5790,
        5757,
        5672,
        5866,
        5829
      ]
    }
  ]
}